{"total":35,"engines":{"boa":35,"jsc":35,"jsc_exp":35,"kiesel":35,"libjs":35,"porffor":21,"qjs":35,"qjs_ng":35,"sm":35,"sm_exp":35,"v8":35,"v8_exp":35},"files":{"built-ins/Symbol/prototype/constructor.js":{"total":1,"engines":{"boa":1,"jsc":1,"jsc_exp":1,"kiesel":1,"libjs":1,"porffor":0,"qjs":1,"qjs_ng":1,"sm":1,"sm_exp":1,"v8":1,"v8_exp":1}},"built-ins/Symbol/prototype/description":{"total":7,"engines":{"boa":7,"jsc":7,"jsc_exp":7,"kiesel":7,"libjs":7,"porffor":4,"qjs":7,"qjs_ng":7,"sm":7,"sm_exp":7,"v8":7,"v8_exp":7}},"built-ins/Symbol/prototype/intrinsic.js":{"total":1,"engines":{"boa":1,"jsc":1,"jsc_exp":1,"kiesel":1,"libjs":1,"porffor":1,"qjs":1,"qjs_ng":1,"sm":1,"sm_exp":1,"v8":1,"v8_exp":1}},"built-ins/Symbol/prototype/Symbol.toPrimitive":{"total":9,"engines":{"boa":9,"jsc":9,"jsc_exp":9,"kiesel":9,"libjs":9,"porffor":1,"qjs":9,"qjs_ng":9,"sm":9,"sm_exp":9,"v8":9,"v8_exp":9}},"built-ins/Symbol/prototype/Symbol.toStringTag.js":{"total":1,"engines":{"boa":1,"jsc":1,"jsc_exp":1,"kiesel":1,"libjs":1,"porffor":0,"qjs":1,"qjs_ng":1,"sm":1,"sm_exp":1,"v8":1,"v8_exp":1}},"built-ins/Symbol/prototype/toString":{"total":8,"engines":{"boa":8,"jsc":8,"jsc_exp":8,"kiesel":8,"libjs":8,"porffor":7,"qjs":8,"qjs_ng":8,"sm":8,"sm_exp":8,"v8":8,"v8_exp":8}},"built-ins/Symbol/prototype/valueOf":{"total":8,"engines":{"boa":8,"jsc":8,"jsc_exp":8,"kiesel":8,"libjs":8,"porffor":8,"qjs":8,"qjs_ng":8,"sm":8,"sm_exp":8,"v8":8,"v8_exp":8}}}}