{"total":26,"engines":{"jsc":26,"jsc_exp":26,"kiesel":26,"libjs":26,"porffor":12,"qjs":26,"qjs_ng":26,"sm":26,"sm_exp":26,"v8":26,"v8_exp":26},"files":{"built-ins/RegExp/prototype/Symbol.matchAll/isregexp-called-once.js":{"total":1,"engines":{"jsc":1,"jsc_exp":1,"kiesel":1,"libjs":1,"porffor":0,"qjs":1,"qjs_ng":1,"sm":1,"sm_exp":1,"v8":1,"v8_exp":1}},"built-ins/RegExp/prototype/Symbol.matchAll/isregexp-this-throws.js":{"total":1,"engines":{"jsc":1,"jsc_exp":1,"kiesel":1,"libjs":1,"porffor":1,"qjs":1,"qjs_ng":1,"sm":1,"sm_exp":1,"v8":1,"v8_exp":1}},"built-ins/RegExp/prototype/Symbol.matchAll/length.js":{"total":1,"engines":{"jsc":1,"jsc_exp":1,"kiesel":1,"libjs":1,"porffor":0,"qjs":1,"qjs_ng":1,"sm":1,"sm_exp":1,"v8":1,"v8_exp":1}},"built-ins/RegExp/prototype/Symbol.matchAll/name.js":{"total":1,"engines":{"jsc":1,"jsc_exp":1,"kiesel":1,"libjs":1,"porffor":0,"qjs":1,"qjs_ng":1,"sm":1,"sm_exp":1,"v8":1,"v8_exp":1}},"built-ins/RegExp/prototype/Symbol.matchAll/not-a-constructor.js":{"total":1,"engines":{"jsc":1,"jsc_exp":1,"kiesel":1,"libjs":1,"porffor":0,"qjs":1,"qjs_ng":1,"sm":1,"sm_exp":1,"v8":1,"v8_exp":1}},"built-ins/RegExp/prototype/Symbol.matchAll/prop-desc.js":{"total":1,"engines":{"jsc":1,"jsc_exp":1,"kiesel":1,"libjs":1,"porffor":0,"qjs":1,"qjs_ng":1,"sm":1,"sm_exp":1,"v8":1,"v8_exp":1}},"built-ins/RegExp/prototype/Symbol.matchAll/regexpcreate-this-throws.js":{"total":1,"engines":{"jsc":1,"jsc_exp":1,"kiesel":1,"libjs":1,"porffor":1,"qjs":1,"qjs_ng":1,"sm":1,"sm_exp":1,"v8":1,"v8_exp":1}},"built-ins/RegExp/prototype/Symbol.matchAll/species-constructor-get-constructor-throws.js":{"total":1,"engines":{"jsc":1,"jsc_exp":1,"kiesel":1,"libjs":1,"porffor":1,"qjs":1,"qjs_ng":1,"sm":1,"sm_exp":1,"v8":1,"v8_exp":1}},"built-ins/RegExp/prototype/Symbol.matchAll/species-constructor-get-species-throws.js":{"total":1,"engines":{"jsc":1,"jsc_exp":1,"kiesel":1,"libjs":1,"porffor":1,"qjs":1,"qjs_ng":1,"sm":1,"sm_exp":1,"v8":1,"v8_exp":1}},"built-ins/RegExp/prototype/Symbol.matchAll/species-constructor-is-not-object-throws.js":{"total":1,"engines":{"jsc":1,"jsc_exp":1,"kiesel":1,"libjs":1,"porffor":1,"qjs":1,"qjs_ng":1,"sm":1,"sm_exp":1,"v8":1,"v8_exp":1}},"built-ins/RegExp/prototype/Symbol.matchAll/species-constructor-is-undefined.js":{"total":1,"engines":{"jsc":1,"jsc_exp":1,"kiesel":1,"libjs":1,"porffor":0,"qjs":1,"qjs_ng":1,"sm":1,"sm_exp":1,"v8":1,"v8_exp":1}},"built-ins/RegExp/prototype/Symbol.matchAll/species-constructor-species-is-not-constructor.js":{"total":1,"engines":{"jsc":1,"jsc_exp":1,"kiesel":1,"libjs":1,"porffor":1,"qjs":1,"qjs_ng":1,"sm":1,"sm_exp":1,"v8":1,"v8_exp":1}},"built-ins/RegExp/prototype/Symbol.matchAll/species-constructor-species-is-null-or-undefined.js":{"total":1,"engines":{"jsc":1,"jsc_exp":1,"kiesel":1,"libjs":1,"porffor":0,"qjs":1,"qjs_ng":1,"sm":1,"sm_exp":1,"v8":1,"v8_exp":1}},"built-ins/RegExp/prototype/Symbol.matchAll/species-constructor-species-throws.js":{"total":1,"engines":{"jsc":1,"jsc_exp":1,"kiesel":1,"libjs":1,"porffor":1,"qjs":1,"qjs_ng":1,"sm":1,"sm_exp":1,"v8":1,"v8_exp":1}},"built-ins/RegExp/prototype/Symbol.matchAll/species-constructor.js":{"total":1,"engines":{"jsc":1,"jsc_exp":1,"kiesel":1,"libjs":1,"porffor":0,"qjs":1,"qjs_ng":1,"sm":1,"sm_exp":1,"v8":1,"v8_exp":1}},"built-ins/RegExp/prototype/Symbol.matchAll/species-regexp-get-global-throws.js":{"total":1,"engines":{"jsc":1,"jsc_exp":1,"kiesel":1,"libjs":1,"porffor":0,"qjs":1,"qjs_ng":1,"sm":1,"sm_exp":1,"v8":1,"v8_exp":1}},"built-ins/RegExp/prototype/Symbol.matchAll/species-regexp-get-unicode-throws.js":{"total":1,"engines":{"jsc":1,"jsc_exp":1,"kiesel":1,"libjs":1,"porffor":0,"qjs":1,"qjs_ng":1,"sm":1,"sm_exp":1,"v8":1,"v8_exp":1}},"built-ins/RegExp/prototype/Symbol.matchAll/string-tostring-throws.js":{"total":1,"engines":{"jsc":1,"jsc_exp":1,"kiesel":1,"libjs":1,"porffor":1,"qjs":1,"qjs_ng":1,"sm":1,"sm_exp":1,"v8":1,"v8_exp":1}},"built-ins/RegExp/prototype/Symbol.matchAll/string-tostring.js":{"total":1,"engines":{"jsc":1,"jsc_exp":1,"kiesel":1,"libjs":1,"porffor":0,"qjs":1,"qjs_ng":1,"sm":1,"sm_exp":1,"v8":1,"v8_exp":1}},"built-ins/RegExp/prototype/Symbol.matchAll/this-get-flags-throws.js":{"total":1,"engines":{"jsc":1,"jsc_exp":1,"kiesel":1,"libjs":1,"porffor":1,"qjs":1,"qjs_ng":1,"sm":1,"sm_exp":1,"v8":1,"v8_exp":1}},"built-ins/RegExp/prototype/Symbol.matchAll/this-get-flags.js":{"total":1,"engines":{"jsc":1,"jsc_exp":1,"kiesel":1,"libjs":1,"porffor":0,"qjs":1,"qjs_ng":1,"sm":1,"sm_exp":1,"v8":1,"v8_exp":1}},"built-ins/RegExp/prototype/Symbol.matchAll/this-lastindex-cached.js":{"total":1,"engines":{"jsc":1,"jsc_exp":1,"kiesel":1,"libjs":1,"porffor":0,"qjs":1,"qjs_ng":1,"sm":1,"sm_exp":1,"v8":1,"v8_exp":1}},"built-ins/RegExp/prototype/Symbol.matchAll/this-not-object-throws.js":{"total":1,"engines":{"jsc":1,"jsc_exp":1,"kiesel":1,"libjs":1,"porffor":1,"qjs":1,"qjs_ng":1,"sm":1,"sm_exp":1,"v8":1,"v8_exp":1}},"built-ins/RegExp/prototype/Symbol.matchAll/this-tolength-lastindex-throws.js":{"total":1,"engines":{"jsc":1,"jsc_exp":1,"kiesel":1,"libjs":1,"porffor":1,"qjs":1,"qjs_ng":1,"sm":1,"sm_exp":1,"v8":1,"v8_exp":1}},"built-ins/RegExp/prototype/Symbol.matchAll/this-tostring-flags-throws.js":{"total":1,"engines":{"jsc":1,"jsc_exp":1,"kiesel":1,"libjs":1,"porffor":1,"qjs":1,"qjs_ng":1,"sm":1,"sm_exp":1,"v8":1,"v8_exp":1}},"built-ins/RegExp/prototype/Symbol.matchAll/this-tostring-flags.js":{"total":1,"engines":{"jsc":1,"jsc_exp":1,"kiesel":1,"libjs":1,"porffor":0,"qjs":1,"qjs_ng":1,"sm":1,"sm_exp":1,"v8":1,"v8_exp":1}}}}