{"total":23,"engines":{"boa":23,"jsc":23,"jsc_exp":23,"kiesel":23,"libjs":23,"porffor":13,"qjs":19,"qjs_ng":23,"sm":23,"sm_exp":23,"v8":23,"v8_exp":23},"files":{"built-ins/Array/prototype/findIndex/array-altered-during-loop.js":{"total":1,"engines":{"boa":1,"jsc":1,"jsc_exp":1,"kiesel":1,"libjs":1,"porffor":1,"qjs":1,"qjs_ng":1,"sm":1,"sm_exp":1,"v8":1,"v8_exp":1}},"built-ins/Array/prototype/findIndex/call-with-boolean.js":{"total":1,"engines":{"boa":1,"jsc":1,"jsc_exp":1,"kiesel":1,"libjs":1,"porffor":0,"qjs":1,"qjs_ng":1,"sm":1,"sm_exp":1,"v8":1,"v8_exp":1}},"built-ins/Array/prototype/findIndex/callbackfn-resize-arraybuffer.js":{"total":1,"engines":{"boa":1,"jsc":1,"jsc_exp":1,"kiesel":1,"libjs":1,"porffor":0,"qjs":0,"qjs_ng":1,"sm":1,"sm_exp":1,"v8":1,"v8_exp":1}},"built-ins/Array/prototype/findIndex/length.js":{"total":1,"engines":{"boa":1,"jsc":1,"jsc_exp":1,"kiesel":1,"libjs":1,"porffor":0,"qjs":1,"qjs_ng":1,"sm":1,"sm_exp":1,"v8":1,"v8_exp":1}},"built-ins/Array/prototype/findIndex/name.js":{"total":1,"engines":{"boa":1,"jsc":1,"jsc_exp":1,"kiesel":1,"libjs":1,"porffor":1,"qjs":1,"qjs_ng":1,"sm":1,"sm_exp":1,"v8":1,"v8_exp":1}},"built-ins/Array/prototype/findIndex/not-a-constructor.js":{"total":1,"engines":{"boa":1,"jsc":1,"jsc_exp":1,"kiesel":1,"libjs":1,"porffor":1,"qjs":1,"qjs_ng":1,"sm":1,"sm_exp":1,"v8":1,"v8_exp":1}},"built-ins/Array/prototype/findIndex/predicate-call-parameters.js":{"total":1,"engines":{"boa":1,"jsc":1,"jsc_exp":1,"kiesel":1,"libjs":1,"porffor":1,"qjs":1,"qjs_ng":1,"sm":1,"sm_exp":1,"v8":1,"v8_exp":1}},"built-ins/Array/prototype/findIndex/predicate-call-this-non-strict.js":{"total":1,"engines":{"boa":1,"jsc":1,"jsc_exp":1,"kiesel":1,"libjs":1,"porffor":1,"qjs":1,"qjs_ng":1,"sm":1,"sm_exp":1,"v8":1,"v8_exp":1}},"built-ins/Array/prototype/findIndex/predicate-call-this-strict.js":{"total":1,"engines":{"boa":1,"jsc":1,"jsc_exp":1,"kiesel":1,"libjs":1,"porffor":1,"qjs":1,"qjs_ng":1,"sm":1,"sm_exp":1,"v8":1,"v8_exp":1}},"built-ins/Array/prototype/findIndex/predicate-called-for-each-array-property.js":{"total":1,"engines":{"boa":1,"jsc":1,"jsc_exp":1,"kiesel":1,"libjs":1,"porffor":1,"qjs":1,"qjs_ng":1,"sm":1,"sm_exp":1,"v8":1,"v8_exp":1}},"built-ins/Array/prototype/findIndex/predicate-is-not-callable-throws.js":{"total":1,"engines":{"boa":1,"jsc":1,"jsc_exp":1,"kiesel":1,"libjs":1,"porffor":0,"qjs":1,"qjs_ng":1,"sm":1,"sm_exp":1,"v8":1,"v8_exp":1}},"built-ins/Array/prototype/findIndex/predicate-not-called-on-empty-array.js":{"total":1,"engines":{"boa":1,"jsc":1,"jsc_exp":1,"kiesel":1,"libjs":1,"porffor":0,"qjs":1,"qjs_ng":1,"sm":1,"sm_exp":1,"v8":1,"v8_exp":1}},"built-ins/Array/prototype/findIndex/prop-desc.js":{"total":1,"engines":{"boa":1,"jsc":1,"jsc_exp":1,"kiesel":1,"libjs":1,"porffor":1,"qjs":1,"qjs_ng":1,"sm":1,"sm_exp":1,"v8":1,"v8_exp":1}},"built-ins/Array/prototype/findIndex/resizable-buffer-grow-mid-iteration.js":{"total":1,"engines":{"boa":1,"jsc":1,"jsc_exp":1,"kiesel":1,"libjs":1,"porffor":0,"qjs":0,"qjs_ng":1,"sm":1,"sm_exp":1,"v8":1,"v8_exp":1}},"built-ins/Array/prototype/findIndex/resizable-buffer-shrink-mid-iteration.js":{"total":1,"engines":{"boa":1,"jsc":1,"jsc_exp":1,"kiesel":1,"libjs":1,"porffor":0,"qjs":0,"qjs_ng":1,"sm":1,"sm_exp":1,"v8":1,"v8_exp":1}},"built-ins/Array/prototype/findIndex/resizable-buffer.js":{"total":1,"engines":{"boa":1,"jsc":1,"jsc_exp":1,"kiesel":1,"libjs":1,"porffor":0,"qjs":0,"qjs_ng":1,"sm":1,"sm_exp":1,"v8":1,"v8_exp":1}},"built-ins/Array/prototype/findIndex/return-abrupt-from-predicate-call.js":{"total":1,"engines":{"boa":1,"jsc":1,"jsc_exp":1,"kiesel":1,"libjs":1,"porffor":1,"qjs":1,"qjs_ng":1,"sm":1,"sm_exp":1,"v8":1,"v8_exp":1}},"built-ins/Array/prototype/findIndex/return-abrupt-from-property.js":{"total":1,"engines":{"boa":1,"jsc":1,"jsc_exp":1,"kiesel":1,"libjs":1,"porffor":1,"qjs":1,"qjs_ng":1,"sm":1,"sm_exp":1,"v8":1,"v8_exp":1}},"built-ins/Array/prototype/findIndex/return-abrupt-from-this-length-as-symbol.js":{"total":1,"engines":{"boa":1,"jsc":1,"jsc_exp":1,"kiesel":1,"libjs":1,"porffor":1,"qjs":1,"qjs_ng":1,"sm":1,"sm_exp":1,"v8":1,"v8_exp":1}},"built-ins/Array/prototype/findIndex/return-abrupt-from-this-length.js":{"total":1,"engines":{"boa":1,"jsc":1,"jsc_exp":1,"kiesel":1,"libjs":1,"porffor":1,"qjs":1,"qjs_ng":1,"sm":1,"sm_exp":1,"v8":1,"v8_exp":1}},"built-ins/Array/prototype/findIndex/return-abrupt-from-this.js":{"total":1,"engines":{"boa":1,"jsc":1,"jsc_exp":1,"kiesel":1,"libjs":1,"porffor":1,"qjs":1,"qjs_ng":1,"sm":1,"sm_exp":1,"v8":1,"v8_exp":1}},"built-ins/Array/prototype/findIndex/return-index-predicate-result-is-true.js":{"total":1,"engines":{"boa":1,"jsc":1,"jsc_exp":1,"kiesel":1,"libjs":1,"porffor":0,"qjs":1,"qjs_ng":1,"sm":1,"sm_exp":1,"v8":1,"v8_exp":1}},"built-ins/Array/prototype/findIndex/return-negative-one-if-predicate-returns-false-value.js":{"total":1,"engines":{"boa":1,"jsc":1,"jsc_exp":1,"kiesel":1,"libjs":1,"porffor":0,"qjs":1,"qjs_ng":1,"sm":1,"sm_exp":1,"v8":1,"v8_exp":1}}}}