{"total":41,"engines":{"boa":41,"jsc":0,"jsc_exp":21,"kiesel":3,"libjs":41,"porffor":0,"qjs":0,"qjs_ng":0,"sm":41,"sm_exp":41,"v8":0,"v8_exp":5},"files":{"built-ins/Temporal/PlainDate/prototype/add/add-days.js":{"total":1,"engines":{"boa":1,"jsc":0,"jsc_exp":0,"kiesel":0,"libjs":1,"porffor":0,"qjs":0,"qjs_ng":0,"sm":1,"sm_exp":1,"v8":0,"v8_exp":0}},"built-ins/Temporal/PlainDate/prototype/add/add-months-weeks.js":{"total":1,"engines":{"boa":1,"jsc":0,"jsc_exp":0,"kiesel":0,"libjs":1,"porffor":0,"qjs":0,"qjs_ng":0,"sm":1,"sm_exp":1,"v8":0,"v8_exp":0}},"built-ins/Temporal/PlainDate/prototype/add/add-months.js":{"total":1,"engines":{"boa":1,"jsc":0,"jsc_exp":0,"kiesel":0,"libjs":1,"porffor":0,"qjs":0,"qjs_ng":0,"sm":1,"sm_exp":1,"v8":0,"v8_exp":0}},"built-ins/Temporal/PlainDate/prototype/add/add-weeks-days.js":{"total":1,"engines":{"boa":1,"jsc":0,"jsc_exp":0,"kiesel":0,"libjs":1,"porffor":0,"qjs":0,"qjs_ng":0,"sm":1,"sm_exp":1,"v8":0,"v8_exp":0}},"built-ins/Temporal/PlainDate/prototype/add/add-weeks.js":{"total":1,"engines":{"boa":1,"jsc":0,"jsc_exp":0,"kiesel":0,"libjs":1,"porffor":0,"qjs":0,"qjs_ng":0,"sm":1,"sm_exp":1,"v8":0,"v8_exp":0}},"built-ins/Temporal/PlainDate/prototype/add/add-years-months-days.js":{"total":1,"engines":{"boa":1,"jsc":0,"jsc_exp":0,"kiesel":0,"libjs":1,"porffor":0,"qjs":0,"qjs_ng":0,"sm":1,"sm_exp":1,"v8":0,"v8_exp":0}},"built-ins/Temporal/PlainDate/prototype/add/add-years-months.js":{"total":1,"engines":{"boa":1,"jsc":0,"jsc_exp":0,"kiesel":0,"libjs":1,"porffor":0,"qjs":0,"qjs_ng":0,"sm":1,"sm_exp":1,"v8":0,"v8_exp":0}},"built-ins/Temporal/PlainDate/prototype/add/add-years-weeks.js":{"total":1,"engines":{"boa":1,"jsc":0,"jsc_exp":0,"kiesel":0,"libjs":1,"porffor":0,"qjs":0,"qjs_ng":0,"sm":1,"sm_exp":1,"v8":0,"v8_exp":0}},"built-ins/Temporal/PlainDate/prototype/add/add-years.js":{"total":1,"engines":{"boa":1,"jsc":0,"jsc_exp":0,"kiesel":0,"libjs":1,"porffor":0,"qjs":0,"qjs_ng":0,"sm":1,"sm_exp":1,"v8":0,"v8_exp":0}},"built-ins/Temporal/PlainDate/prototype/add/argument-duration-max.js":{"total":1,"engines":{"boa":1,"jsc":0,"jsc_exp":0,"kiesel":0,"libjs":1,"porffor":0,"qjs":0,"qjs_ng":0,"sm":1,"sm_exp":1,"v8":0,"v8_exp":0}},"built-ins/Temporal/PlainDate/prototype/add/argument-duration-out-of-range.js":{"total":1,"engines":{"boa":1,"jsc":0,"jsc_exp":1,"kiesel":0,"libjs":1,"porffor":0,"qjs":0,"qjs_ng":0,"sm":1,"sm_exp":1,"v8":0,"v8_exp":0}},"built-ins/Temporal/PlainDate/prototype/add/argument-invalid-property.js":{"total":1,"engines":{"boa":1,"jsc":0,"jsc_exp":1,"kiesel":1,"libjs":1,"porffor":0,"qjs":0,"qjs_ng":0,"sm":1,"sm_exp":1,"v8":0,"v8_exp":0}},"built-ins/Temporal/PlainDate/prototype/add/argument-mixed-sign.js":{"total":1,"engines":{"boa":1,"jsc":0,"jsc_exp":1,"kiesel":0,"libjs":1,"porffor":0,"qjs":0,"qjs_ng":0,"sm":1,"sm_exp":1,"v8":0,"v8_exp":0}},"built-ins/Temporal/PlainDate/prototype/add/argument-not-object.js":{"total":1,"engines":{"boa":1,"jsc":0,"jsc_exp":1,"kiesel":0,"libjs":1,"porffor":0,"qjs":0,"qjs_ng":0,"sm":1,"sm_exp":1,"v8":0,"v8_exp":0}},"built-ins/Temporal/PlainDate/prototype/add/argument-singular-properties.js":{"total":1,"engines":{"boa":1,"jsc":0,"jsc_exp":1,"kiesel":1,"libjs":1,"porffor":0,"qjs":0,"qjs_ng":0,"sm":1,"sm_exp":1,"v8":0,"v8_exp":0}},"built-ins/Temporal/PlainDate/prototype/add/argument-string-invalid.js":{"total":1,"engines":{"boa":1,"jsc":0,"jsc_exp":1,"kiesel":0,"libjs":1,"porffor":0,"qjs":0,"qjs_ng":0,"sm":1,"sm_exp":1,"v8":0,"v8_exp":0}},"built-ins/Temporal/PlainDate/prototype/add/argument-string-negative-fractional-units.js":{"total":1,"engines":{"boa":1,"jsc":0,"jsc_exp":0,"kiesel":0,"libjs":1,"porffor":0,"qjs":0,"qjs_ng":0,"sm":1,"sm_exp":1,"v8":0,"v8_exp":0}},"built-ins/Temporal/PlainDate/prototype/add/argument-string.js":{"total":1,"engines":{"boa":1,"jsc":0,"jsc_exp":0,"kiesel":0,"libjs":1,"porffor":0,"qjs":0,"qjs_ng":0,"sm":1,"sm_exp":1,"v8":0,"v8_exp":0}},"built-ins/Temporal/PlainDate/prototype/add/balance-smaller-units-basic.js":{"total":1,"engines":{"boa":1,"jsc":0,"jsc_exp":0,"kiesel":0,"libjs":1,"porffor":0,"qjs":0,"qjs_ng":0,"sm":1,"sm_exp":1,"v8":0,"v8_exp":0}},"built-ins/Temporal/PlainDate/prototype/add/balance-smaller-units.js":{"total":1,"engines":{"boa":1,"jsc":0,"jsc_exp":0,"kiesel":0,"libjs":1,"porffor":0,"qjs":0,"qjs_ng":0,"sm":1,"sm_exp":1,"v8":0,"v8_exp":0}},"built-ins/Temporal/PlainDate/prototype/add/basic.js":{"total":1,"engines":{"boa":1,"jsc":0,"jsc_exp":0,"kiesel":0,"libjs":1,"porffor":0,"qjs":0,"qjs_ng":0,"sm":1,"sm_exp":1,"v8":0,"v8_exp":0}},"built-ins/Temporal/PlainDate/prototype/add/branding.js":{"total":1,"engines":{"boa":1,"jsc":0,"jsc_exp":1,"kiesel":0,"libjs":1,"porffor":0,"qjs":0,"qjs_ng":0,"sm":1,"sm_exp":1,"v8":0,"v8_exp":0}},"built-ins/Temporal/PlainDate/prototype/add/builtin.js":{"total":1,"engines":{"boa":1,"jsc":0,"jsc_exp":1,"kiesel":0,"libjs":1,"porffor":0,"qjs":0,"qjs_ng":0,"sm":1,"sm_exp":1,"v8":0,"v8_exp":1}},"built-ins/Temporal/PlainDate/prototype/add/infinity-throws-rangeerror.js":{"total":1,"engines":{"boa":1,"jsc":0,"jsc_exp":1,"kiesel":0,"libjs":1,"porffor":0,"qjs":0,"qjs_ng":0,"sm":1,"sm_exp":1,"v8":0,"v8_exp":0}},"built-ins/Temporal/PlainDate/prototype/add/length.js":{"total":1,"engines":{"boa":1,"jsc":0,"jsc_exp":1,"kiesel":0,"libjs":1,"porffor":0,"qjs":0,"qjs_ng":0,"sm":1,"sm_exp":1,"v8":0,"v8_exp":1}},"built-ins/Temporal/PlainDate/prototype/add/limits.js":{"total":1,"engines":{"boa":1,"jsc":0,"jsc_exp":1,"kiesel":0,"libjs":1,"porffor":0,"qjs":0,"qjs_ng":0,"sm":1,"sm_exp":1,"v8":0,"v8_exp":0}},"built-ins/Temporal/PlainDate/prototype/add/name.js":{"total":1,"engines":{"boa":1,"jsc":0,"jsc_exp":1,"kiesel":0,"libjs":1,"porffor":0,"qjs":0,"qjs_ng":0,"sm":1,"sm_exp":1,"v8":0,"v8_exp":1}},"built-ins/Temporal/PlainDate/prototype/add/negative-infinity-throws-rangeerror.js":{"total":1,"engines":{"boa":1,"jsc":0,"jsc_exp":1,"kiesel":0,"libjs":1,"porffor":0,"qjs":0,"qjs_ng":0,"sm":1,"sm_exp":1,"v8":0,"v8_exp":0}},"built-ins/Temporal/PlainDate/prototype/add/non-integer-throws-rangeerror.js":{"total":1,"engines":{"boa":1,"jsc":0,"jsc_exp":1,"kiesel":0,"libjs":1,"porffor":0,"qjs":0,"qjs_ng":0,"sm":1,"sm_exp":1,"v8":0,"v8_exp":0}},"built-ins/Temporal/PlainDate/prototype/add/not-a-constructor.js":{"total":1,"engines":{"boa":1,"jsc":0,"jsc_exp":1,"kiesel":0,"libjs":1,"porffor":0,"qjs":0,"qjs_ng":0,"sm":1,"sm_exp":1,"v8":0,"v8_exp":1}},"built-ins/Temporal/PlainDate/prototype/add/options-object.js":{"total":1,"engines":{"boa":1,"jsc":0,"jsc_exp":0,"kiesel":0,"libjs":1,"porffor":0,"qjs":0,"qjs_ng":0,"sm":1,"sm_exp":1,"v8":0,"v8_exp":0}},"built-ins/Temporal/PlainDate/prototype/add/options-undefined.js":{"total":1,"engines":{"boa":1,"jsc":0,"jsc_exp":1,"kiesel":0,"libjs":1,"porffor":0,"qjs":0,"qjs_ng":0,"sm":1,"sm_exp":1,"v8":0,"v8_exp":0}},"built-ins/Temporal/PlainDate/prototype/add/options-wrong-type.js":{"total":1,"engines":{"boa":1,"jsc":0,"jsc_exp":1,"kiesel":1,"libjs":1,"porffor":0,"qjs":0,"qjs_ng":0,"sm":1,"sm_exp":1,"v8":0,"v8_exp":0}},"built-ins/Temporal/PlainDate/prototype/add/order-of-operations.js":{"total":1,"engines":{"boa":1,"jsc":0,"jsc_exp":1,"kiesel":0,"libjs":1,"porffor":0,"qjs":0,"qjs_ng":0,"sm":1,"sm_exp":1,"v8":0,"v8_exp":0}},"built-ins/Temporal/PlainDate/prototype/add/overflow-constrain.js":{"total":1,"engines":{"boa":1,"jsc":0,"jsc_exp":0,"kiesel":0,"libjs":1,"porffor":0,"qjs":0,"qjs_ng":0,"sm":1,"sm_exp":1,"v8":0,"v8_exp":0}},"built-ins/Temporal/PlainDate/prototype/add/overflow-invalid-string.js":{"total":1,"engines":{"boa":1,"jsc":0,"jsc_exp":1,"kiesel":0,"libjs":1,"porffor":0,"qjs":0,"qjs_ng":0,"sm":1,"sm_exp":1,"v8":0,"v8_exp":0}},"built-ins/Temporal/PlainDate/prototype/add/overflow-reject.js":{"total":1,"engines":{"boa":1,"jsc":0,"jsc_exp":1,"kiesel":0,"libjs":1,"porffor":0,"qjs":0,"qjs_ng":0,"sm":1,"sm_exp":1,"v8":0,"v8_exp":0}},"built-ins/Temporal/PlainDate/prototype/add/overflow-undefined.js":{"total":1,"engines":{"boa":1,"jsc":0,"jsc_exp":0,"kiesel":0,"libjs":1,"porffor":0,"qjs":0,"qjs_ng":0,"sm":1,"sm_exp":1,"v8":0,"v8_exp":0}},"built-ins/Temporal/PlainDate/prototype/add/overflow-wrong-type.js":{"total":1,"engines":{"boa":1,"jsc":0,"jsc_exp":0,"kiesel":0,"libjs":1,"porffor":0,"qjs":0,"qjs_ng":0,"sm":1,"sm_exp":1,"v8":0,"v8_exp":0}},"built-ins/Temporal/PlainDate/prototype/add/prop-desc.js":{"total":1,"engines":{"boa":1,"jsc":0,"jsc_exp":1,"kiesel":0,"libjs":1,"porffor":0,"qjs":0,"qjs_ng":0,"sm":1,"sm_exp":1,"v8":0,"v8_exp":1}},"built-ins/Temporal/PlainDate/prototype/add/subclassing-ignored.js":{"total":1,"engines":{"boa":1,"jsc":0,"jsc_exp":0,"kiesel":0,"libjs":1,"porffor":0,"qjs":0,"qjs_ng":0,"sm":1,"sm_exp":1,"v8":0,"v8_exp":0}}}}